_tdvutil/__init__.py
_tdvutil/_version.py
_tdvutil/alintrospect.py
_tdvutil/argparse.py
_tdvutil/now.py
_tdvutil/pathfix.py
_tdvutil/ppretty.py
_tdvutil/ppretty.pyi
_tdvutil/py.typed
_tdvutil/timefmt.py
tdvutil/__init__.py
tdvutil/py.typed
tdvutil/argparse/__init__.py
tdvutil-0.0.9.dist-info/LICENSE.txt
tdvutil-0.0.9.dist-info/METADATA
tdvutil-0.0.9.dist-info/WHEEL
tdvutil-0.0.9.dist-info/top_level.txt
tdvutil-0.0.9.dist-info/RECORD
