Metadata-Version: 2.1
Name: tdvutil
Version: 0.0.9
Summary: A few simple helper classes used by TDV Alinsa
Author-email: TDV Alinsa <alinsa-github@lupine.org>
License: GNU GENERAL PUBLIC LICENSE
Project-URL: Homepage, https://github.com/alinsavix/python-tdvutil
Project-URL: Bug Reports, https://github.com/alinsavix/python-tdvutil/issues
Project-URL: Source, https://github.com/alinsavix/python-tdvutil
Classifier: Development Status :: 3 - Alpha
Classifier: Intended Audience :: Developers
Classifier: License :: OSI Approved :: GNU General Public License v3 (GPLv3)
Classifier: Programming Language :: Python :: 3
Classifier: Topic :: Software Development :: Libraries
Requires-Python: >=3.9
License-File: LICENSE.txt
Provides-Extra: tests
Requires-Dist: pytest (>=7.0) ; extra == 'tests'
Requires-Dist: pytest-cov ; extra == 'tests'
